setup.py
isi_sdk_8_2_2/__init__.py
isi_sdk_8_2_2/api_client.py
isi_sdk_8_2_2/configuration.py
isi_sdk_8_2_2/rest.py
isi_sdk_8_2_2.egg-info/PKG-INFO
isi_sdk_8_2_2.egg-info/SOURCES.txt
isi_sdk_8_2_2.egg-info/dependency_links.txt
isi_sdk_8_2_2.egg-info/requires.txt
isi_sdk_8_2_2.egg-info/top_level.txt
isi_sdk_8_2_2/api/__init__.py
isi_sdk_8_2_2/api/antivirus_api.py
isi_sdk_8_2_2/api/audit_api.py
isi_sdk_8_2_2/api/auth_api.py
isi_sdk_8_2_2/api/auth_groups_api.py
isi_sdk_8_2_2/api/auth_providers_api.py
isi_sdk_8_2_2/api/auth_roles_api.py
isi_sdk_8_2_2/api/auth_users_api.py
isi_sdk_8_2_2/api/certificate_api.py
isi_sdk_8_2_2/api/cloud_api.py
isi_sdk_8_2_2/api/cluster_api.py
isi_sdk_8_2_2/api/cluster_nodes_api.py
isi_sdk_8_2_2/api/debug_api.py
isi_sdk_8_2_2/api/dedupe_api.py
isi_sdk_8_2_2/api/event_api.py
isi_sdk_8_2_2/api/file_filter_api.py
isi_sdk_8_2_2/api/filepool_api.py
isi_sdk_8_2_2/api/filesystem_api.py
isi_sdk_8_2_2/api/fsa_api.py
isi_sdk_8_2_2/api/fsa_index_api.py
isi_sdk_8_2_2/api/fsa_results_api.py
isi_sdk_8_2_2/api/groupnets_summary_api.py
isi_sdk_8_2_2/api/hardening_api.py
isi_sdk_8_2_2/api/hardware_api.py
isi_sdk_8_2_2/api/healthcheck_api.py
isi_sdk_8_2_2/api/id_resolution_api.py
isi_sdk_8_2_2/api/id_resolution_zones_api.py
isi_sdk_8_2_2/api/job_api.py
isi_sdk_8_2_2/api/license_api.py
isi_sdk_8_2_2/api/local_api.py
isi_sdk_8_2_2/api/local_cluster_api.py
isi_sdk_8_2_2/api/namespace_api.py
isi_sdk_8_2_2/api/network_api.py
isi_sdk_8_2_2/api/network_groupnets_api.py
isi_sdk_8_2_2/api/network_groupnets_subnets_api.py
isi_sdk_8_2_2/api/performance_api.py
isi_sdk_8_2_2/api/performance_datasets_api.py
isi_sdk_8_2_2/api/protocols_api.py
isi_sdk_8_2_2/api/protocols_hdfs_api.py
isi_sdk_8_2_2/api/quota_api.py
isi_sdk_8_2_2/api/quota_quotas_api.py
isi_sdk_8_2_2/api/quota_reports_api.py
isi_sdk_8_2_2/api/remotesupport_api.py
isi_sdk_8_2_2/api/snapshot_api.py
isi_sdk_8_2_2/api/snapshot_changelists_api.py
isi_sdk_8_2_2/api/snapshot_snapshots_api.py
isi_sdk_8_2_2/api/statistics_api.py
isi_sdk_8_2_2/api/storagepool_api.py
isi_sdk_8_2_2/api/sync_api.py
isi_sdk_8_2_2/api/sync_policies_api.py
isi_sdk_8_2_2/api/sync_reports_api.py
